askedith/__init__.py
askedith/config.py
askedith-0.31.2.dist-info/LICENSE
askedith-0.31.2.dist-info/METADATA
askedith-0.31.2.dist-info/WHEEL
askedith-0.31.2.dist-info/top_level.txt
askedith-0.31.2.dist-info/RECORD
