Metadata-Version: 2.1
Name: askedith
Version: 0.31.2
Summary: Natural Language Query Engine for Pandas
Home-page: https://askedith.ai
Author: Jared Zhao
License: Apache 2.0
Platform: UNKNOWN
Requires-Python: >=3.6
License-File: LICENSE
Requires-Dist: requests >=2.0.0
Requires-Dist: pandas
